main.py
ramanager/Database.py
ramanager/Project.py
ramanager/ProjectBase.py
ramanager/ProjectManager.py
ramanager/TextToSpeech.py
ramanager/Year.py
ramanager/__init__.py
ramanager/inputs.py
ramanager/settings/__init__.py
ramanager/settings/control.py
ramanager/settings/types.py
ramanager/templates/PythonPackage/$project_name_snake/build_utils/general.py
colemen_ra_manager-0.2.8.dist-info/METADATA
colemen_ra_manager-0.2.8.dist-info/WHEEL
colemen_ra_manager-0.2.8.dist-info/top_level.txt
colemen_ra_manager-0.2.8.dist-info/RECORD
