Metadata-Version: 2.1
Name: colemen-ra-manager
Version: 0.2.8
Summary: colemen_ra_manager
Author: Colemen Atwood
Author-email: <atwoodcolemen@gmail.com>
Keywords: python
Classifier: Development Status :: 3 - Alpha
Classifier: Intended Audience :: Education
Classifier: Programming Language :: Python :: 2
Classifier: Programming Language :: Python :: 3
Classifier: Operating System :: MacOS :: MacOS X
Classifier: Operating System :: Microsoft :: Windows
Requires-Dist: colemen-utils
